py_taplo/__init__.py
py_taplo/cli.py
py_taplo/config.py
py_taplo/exception_handler.py
py_taplo/shell.py
py_taplo/taplo.py
py_taplo/version.py
py_taplo-0.1.2.dist-info/entry_points.txt
py_taplo-0.1.2.dist-info/LICENSE
py_taplo-0.1.2.dist-info/WHEEL
py_taplo-0.1.2.dist-info/METADATA
py_taplo-0.1.2.dist-info/RECORD
